Workbook

Sheet Source actuals
A1: AstroDig LLC - Q1 2013 Operating Results
A3: Published 2013-04-15 | USD unless stated | Internal
A5: Q1 2013; period ended 2013-03-31. Company operating ledger and campaign register. Headcount and backlog are period-end snapshots.
A7: Measure | B7: Current period | C7: Units | D7: Available-quarter measure | E7: Q1 2013
A8: Recognized revenue | B8: 120000 | C8: USD | D8: Recognized revenue | E8: 120000
A9: Cost of goods sold | B9: 45600 | C9: USD | D9: Cost of goods sold | E9: 45600
A10: Operating expenses | B10: 358000 | C10: USD | D10: Operating expenses | E10: 358000
A11: Operating result | B11: -283600 | C11: USD | D11: Operating result | E11: -283600
A12: Period-end headcount | B12: 8 | C12: count | D12: Period-end headcount | E12: 8
A13: Engineering services | B13: 90000 | C13: USD | D13: Engineering services | E13: 90000
A14: Instrument development | B14: 18000 | C14: USD | D14: Instrument development | E14: 18000
A15: Mission analysis | B15: 12000 | C15: USD | D15: Mission analysis | E15: 12000
A16: Research and development | B16: 257760 | C16: USD | D16: Research and development | E16: 257760
A17: Program operations | B17: 64440 | C17: USD | D17: Program operations | E17: 64440
A18: Corporate administration | B18: 35800 | C18: USD | D18: Corporate administration | E18: 35800
A19: Contracted backlog | B19: 720000 | C19: USD | D19: Contracted backlog | E19: 720000
... A22: Rejected reference runs | B22: 3 | C22: count | D22: Rejected reference runs | E22: 3
A25: Recognize engineering and development revenue against accepted contracted work; do not recognize projected asteroid sales.
A28: Revenue is recognized against accepted contracted work. No forecast, cash balance, resource valuation, or projected asteroid-sales input is included.

Sheet Income bridge
A1: Income reconciliation
A3: Published 2013-04-15 | USD unless stated | Internal
A5: Does recognized revenue cover delivery and operating costs?
A7: Measure | B7: Value | C7: Check / share
A8: Recognized revenue | B8: ='Source actuals'!B8 -> 120000
A9: Cost of goods sold | B9: ='Source actuals'!B9 -> 45600
A10: Operating expenses | B10: ='Source actuals'!B10 -> 358000
A11: Derived operating result | B11: =B8-B9-B10 -> -283600
A12: Reported operating result | B12: ='Source actuals'!B11 -> -283600
A14: Reconciliation difference | B14: =B11-B12 -> 0 | C14: =IF(B14=0,"RECONCILED","REVIEW") -> RECONCILED
A26: Operating result remains negative after both delivery costs and development spending; the reconciliation isolates the reported loss rather than presenting revenue as profit.
A30: Control: formulas link to source actuals; reconciliation checks must read RECONCILED. Ratios describe the reported period and do not constitute forecast or mission readiness.

Sheet Margins
A1: Margins and spending intensity
A3: Published 2013-04-15 | USD unless stated | Internal
A5: How much revenue remains after delivery costs, and how much is consumed by operating spending?
A7: Measure | B7: Value | C7: Check / share
A8: Revenue | B8: ='Source actuals'!B8 -> 120000
A9: Gross profit | B9: ='Source actuals'!B8-'Source actuals'!B9 -> 74400
A10: Gross margin | B10: =IF(B8=0,0,B9/B8) -> 0.62
A11: Operating margin | B11: =IF(B8=0,0,'Source actuals'!B11/B8) -> -2.3633333
A12: Opex / revenue | B12: =IF(B8=0,0,'Source actuals'!B10/B8) -> 2.9833333
A13: COGS / revenue | B13: =IF(B8=0,0,'Source actuals'!B9/B8) -> 0.38
A15: Gross-margin balance check | B15: =B10+B13-1 -> 0 | C15: =IF(ABS(B15)<0.000001,"RECONCILED","REVIEW") -> RECONCILED
A26: Gross margin and operating margin answer different questions. A positive delivery margin does not imply that the development program is self-financing.
A30: Control: formulas link to source actuals; reconciliation checks must read RECONCILED. Ratios describe the reported period and do not constitute forecast or mission readiness.

Sheet Revenue mix
A1: Service revenue mix
A3: Published 2013-04-15 | USD unless stated | Internal
A5: Which contracted activities produce recognized revenue?
A7: Measure | B7: Value | C7: Check / share
A8: Engineering services | B8: ='Source actuals'!B13 -> 90000 | C8: =IF(B11=0,0,B8/B11) -> 0.75
A9: Instrument development | B9: ='Source actuals'!B14 -> 18000 | C9: =IF(B11=0,0,B9/B11) -> 0.15
A10: Mission analysis | B10: ='Source actuals'!B15 -> 12000 | C10: =IF(B11=0,0,B10/B11) -> 0.1
A11: Allocated total | B11: =SUM(B8:B10) -> 120000 | C11: =SUM(C8:C10) -> 1
A12: Reported total | B12: ='Source actuals'!B8 -> 120000
A14: Allocation difference | B14: =B11-B12 -> 0 | C14: =IF(B14=0,"RECONCILED","REVIEW") -> RECONCILED
A26: Engineering services, instrument development, and mission analysis sum to recognized revenue. No asteroid commodity-sales category is introduced.
A30: Control: formulas link to source actuals; reconciliation checks must read RECONCILED. Ratios describe the reported period and do not constitute forecast or mission readiness.

Sheet Cost drivers
A1: Operating cost allocation
A3: Published 2013-04-15 | USD unless stated | Internal
A5: Where is development capacity being funded?
A7: Measure | B7: Value | C7: Check / share
A8: Research and development | B8: ='Source actuals'!B16 -> 257760 | C8: =IF(B11=0,0,B8/B11) -> 0.72
A9: Program operations | B9: ='Source actuals'!B17 -> 64440 | C9: =IF(B11=0,0,B9/B11) -> 0.18
A10: Corporate administration | B10: ='Source actuals'!B18 -> 35800 | C10: =IF(B11=0,0,B10/B11) -> 0.1
A11: Allocated total | B11: =SUM(B8:B10) -> 358000 | C11: =SUM(C8:C10) -> 1
A12: Reported total | B12: ='Source actuals'!B10 -> 358000
A14: Allocation difference | B14: =B11-B12 -> 0 | C14: =IF(B14=0,"RECONCILED","REVIEW") -> RECONCILED
A26: Research and development, program operations, and corporate administration reconcile to operating expenses. The allocation makes the development priority visible without treating costs as capitalized assets.
A30: Control: formulas link to source actuals; reconciliation checks must read RECONCILED. Ratios describe the reported period and do not constitute forecast or mission readiness.

Sheet Productivity
A1: Workforce and delivery productivity
A3: Published 2013-04-15 | USD unless stated | Internal
A5: What output is supported by the period-end workforce snapshot?
A7: Measure | B7: Value | C7: Check / share
A8: Period-end headcount | B8: ='Source actuals'!B12 -> 8
A9: Revenue / period-end employee | B9: ='Source actuals'!B8/B8 -> 15000
A10: Completed work packages | B10: ='Source actuals'!B20 -> 7
A11: Work packages / employee | B11: =B10/B8 -> 0.875
A12: Accepted reference runs | B12: ='Source actuals'!B21 -> 15
A13: Rejected reference runs | B13: ='Source actuals'!B22 -> 3
A14: Total recorded runs | B14: =SUM(B12:B13) -> 18
A15: Reference acceptance fraction | B15: =IF(B14=0,0,B12/B14) -> 0.83333333
A17: Run-count reconciliation | B17: =B14-B12-B13 -> 0 | C17: =IF(B17=0,"RECONCILED","REVIEW") -> RECONCILED
A26: Revenue and completed work packages per period-end employee are descriptive operating ratios, not labor-efficiency guarantees. Headcount is a point-in-time measure and is not summed across quarters.
A30: Control: formulas link to source actuals; reconciliation checks must read RECONCILED. Ratios describe the reported period and do not constitute forecast or mission readiness.

Sheet Trends and commitments
A1: Available-period trends and commitments
A3: Published 2013-04-15 | USD unless stated | Internal
A5: How do available quarter results and contracted commitments relate?
A7: Measure | B7: Q1 2013 | C7: Check / share
A8: Recognized revenue | B8: ='Source actuals'!E8 -> 120000
A9: Cost of goods sold | B9: ='Source actuals'!E9 -> 45600
A10: Operating expenses | B10: ='Source actuals'!E10 -> 358000
A11: Operating result | B11: ='Source actuals'!E11 -> -283600
A12: Contracted backlog | B12: ='Source actuals'!E19 -> 720000
A13: Period-end headcount | B13: ='Source actuals'!E12 -> 8
A15: Quarter income difference | B15: =B8-B9-B10-B11 -> 0
B16: =IF(B15=0,"RECONCILED","REVIEW") -> RECONCILED
A18: Available-quarter revenue sum | B18: =SUM(B8) -> 120000
A19: Comparison availability | B19: Founding-quarter baseline only
A21: Backlog interpretation | B21: Remaining work; not cash
A26: Quarter trends use only known periods. Backlog is a remaining-work snapshot, not cash or recognized revenue; rejected runs remain visible alongside accepted evidence.
A30: Control: formulas link to source actuals; reconciliation checks must read RECONCILED. Ratios describe the reported period and do not constitute forecast or mission readiness.

Sheet Methodology
A1: Methodology and evidence boundaries
A3: Published 2013-04-15 | USD unless stated | Internal
A5: Period and recognized source actuals: USD; Q1 2013; period ended 2013-03-31. Revenue $120,000; COGS $45,600; opex $358,000; operating result $-283,600. Recognize engineering and development revenue against accepted contracted work; do not recognize projected asteroid sales.
A8: Income reconciliation: Does recognized revenue cover delivery and operating costs? Operating result remains negative after both delivery costs and development spending; the reconciliation isolates the reported loss rather than presenting revenue as profit.
A11: Margins and spending intensity: How much revenue remains after delivery costs, and how much is consumed by operating spending? Gross margin and operating margin answer different questions. A positive delivery margin does not imply that the development program is self-financing.
A14: Service revenue mix: Which contracted activities produce recognized revenue? Engineering services, instrument development, and mission analysis sum to recognized revenue. No asteroid commodity-sales category is introduced.
A17: Operating cost allocation: Where is development capacity being funded? Research and development, program operations, and corporate administration reconcile to operating expenses. The allocation makes the development priority visible without treating costs as capitalized assets.
A20: Workforce and delivery productivity: What output is supported by the period-end workforce snapshot? Revenue and completed work packages per period-end employee are descriptive operating ratios, not labor-efficiency guarantees. Headcount is a point-in-time measure and is not summed across quarters.
A23: Available-period trends and commitments: How do available quarter results and contracted commitments relate? Quarter trends use only known periods. Backlog is a remaining-work snapshot, not cash or recognized revenue; rejected runs remain visible alongside accepted evidence.
A26: Methodology and limitations: Establish traceable engineering baselines before committing to hardware. Principal risk: reference-data consistency. No hardware flight heritage exists. Continue the approved ground-development scope; no asteroid commodity revenue is included in the operating outlook. No forecast, balance sheet, liquidity estimate, resource valuation, or cash-flow conclusion is supplied. Formula-linked analyses use recognized USD amounts and period-end operating snapshots; changing source inputs updates the calculations without changing the stated business scope.
