Workbook

Sheet Source actuals
A1: AstroDig LLC - Q3 2019 Service Economics and Development Spending
A3: Published 2019-10-15 | USD unless stated | Internal
A5: Q3 2019; period ended 2019-09-30. Company operating ledger and campaign register. Headcount and backlog are period-end snapshots.
A7: Measure | B7: Current period | C7: Units | D7: Available-quarter measure | E7: Q1 2019 | F7: Q2 2019 | G7: Q3 2019
A8: Recognized revenue | B8: 2990000 | C8: USD | D8: Recognized revenue | E8: 2300000 | F8: 2645000 | G8: 2990000
A9: Cost of goods sold | B9: 1136200 | C9: USD | D9: Cost of goods sold | E9: 874000 | F9: 1005100 | G9: 1136200
A10: Operating expenses | B10: 3430700 | C10: USD | D10: Operating expenses | E10: 2639000 | F10: 3034850 | G10: 3430700
A11: Operating result | B11: -1576900 | C11: USD | D11: Operating result | E11: -1213000 | F11: -1394950 | G11: -1576900
A12: Period-end headcount | B12: 73 | C12: count | D12: Period-end headcount | E12: 65 | F12: 69 | G12: 73
A13: Engineering services | B13: 2063100 | C13: USD | D13: Engineering services | E13: 1587000 | F13: 1825050 | G13: 2063100
A14: Instrument development | B14: 627900 | C14: USD | D14: Instrument development | E14: 483000 | F14: 555450 | G14: 627900
A15: Mission analysis | B15: 299000 | C15: USD | D15: Mission analysis | E15: 230000 | F15: 264500 | G15: 299000
A16: Research and development | B16: 2470104 | C16: USD | D16: Research and development | E16: 1900080 | F16: 2185092 | G16: 2470104
A17: Program operations | B17: 617526 | C17: USD | D17: Program operations | E17: 475020 | F17: 546273 | G17: 617526
A18: Corporate administration | B18: 343070 | C18: USD | D18: Corporate administration | E18: 263900 | F18: 303485 | G18: 343070
A19: Contracted backlog | B19: 23920000 | C19: USD | D19: Contracted backlog | E19: 13800000 | F19: 18515000 | G19: 23920000
... A22: Rejected reference runs | B22: 6 | C22: count | D22: Rejected reference runs | E22: 4 | F22: 5 | G22: 6
A25: Recognize engineering and development revenue against accepted contracted work; do not recognize projected asteroid sales.
A28: Revenue is recognized against accepted contracted work. No forecast, cash balance, resource valuation, or projected asteroid-sales input is included.

Sheet Income bridge
A1: Income reconciliation
A3: Published 2019-10-15 | USD unless stated | Internal
A5: Does recognized revenue cover delivery and operating costs?
A7: Measure | B7: Value | C7: Check / share
A8: Recognized revenue | B8: ='Source actuals'!B8 -> 2990000
A9: Cost of goods sold | B9: ='Source actuals'!B9 -> 1136200
A10: Operating expenses | B10: ='Source actuals'!B10 -> 3430700
A11: Derived operating result | B11: =B8-B9-B10 -> -1576900
A12: Reported operating result | B12: ='Source actuals'!B11 -> -1576900
A14: Reconciliation difference | B14: =B11-B12 -> 0 | C14: =IF(B14=0,"RECONCILED","REVIEW") -> RECONCILED
A26: Operating result remains negative after both delivery costs and development spending; the reconciliation isolates the reported loss rather than presenting revenue as profit.
A30: Control: formulas link to source actuals; reconciliation checks must read RECONCILED. Ratios describe the reported period and do not constitute forecast or mission readiness.

Sheet Service economics
A1: Contracted service economics
A3: Published 2019-10-15 | USD unless stated | Internal
A5: How do the three service categories reconcile, and what share comes from engineering?
A7: Measure | B7: Value | C7: Check / share
A8: Engineering services | B8: ='Source actuals'!B13 -> 2063100 | C8: =IF(B11=0,0,B8/B11) -> 0.69
A9: Instrument development | B9: ='Source actuals'!B14 -> 627900 | C9: =IF(B11=0,0,B9/B11) -> 0.21
A10: Mission analysis | B10: ='Source actuals'!B15 -> 299000 | C10: =IF(B11=0,0,B10/B11) -> 0.1
A11: Service total | B11: =SUM(B8:B10) -> 2990000
A12: Recognized revenue | B12: ='Source actuals'!B8 -> 2990000
A14: Service reconciliation | B14: =B11-B12 -> 0 | C14: =IF(B14=0,"RECONCILED","REVIEW") -> RECONCILED
A26: Recognized service categories reconcile to revenue. Engineering share describes the revenue base; no category-level profit is inferred because delivery costs are not allocated by service category.
A30: Control: formulas link to source actuals; reconciliation checks must read RECONCILED. Ratios describe the reported period and do not constitute forecast or mission readiness.

Sheet Development intensity
A1: Development spending intensity
A3: Published 2019-10-15 | USD unless stated | Internal
A5: How does research spending relate to revenue, workforce and total operating expense?
A7: Measure | B7: Value | C7: Check / share
A8: Research spending | B8: ='Source actuals'!B16 -> 2470104
A9: Research / revenue | B9: ='Source actuals'!B16/'Source actuals'!B8 -> 0.82612174
A10: Research / period-end employee | B10: ='Source actuals'!B16/'Source actuals'!B12 -> 33837.041
A11: Research / operating expenses | B11: ='Source actuals'!B16/'Source actuals'!B10 -> 0.72
A12: Program operations | B12: ='Source actuals'!B17 -> 617526
A13: Administration | B13: ='Source actuals'!B18 -> 343070
A14: Expense allocation difference | B14: =B8+B12+B13-'Source actuals'!B10 -> 0 | C14: =IF(B14=0,"RECONCILED","REVIEW") -> RECONCILED
A26: Research spending per period-end employee and relative to revenue exposes the development load. These ratios are descriptive; no capitalization, cash burn or return on investment is inferred.
A30: Control: formulas link to source actuals; reconciliation checks must read RECONCILED. Ratios describe the reported period and do not constitute forecast or mission readiness.

Sheet Delivery capacity
A1: Delivery capacity and evidence quality
A3: Published 2019-10-15 | USD unless stated | Internal
A5: How do delivered work and accepted or rejected trials relate to the workforce snapshot?
A7: Measure | B7: Value | C7: Check / share
A8: Period-end headcount | B8: ='Source actuals'!B12 -> 73
A9: Completed work packages | B9: ='Source actuals'!B20 -> 27
A10: Work packages / employee | B10: =B9/B8 -> 0.36986301
A11: Accepted reference runs | B11: ='Source actuals'!B21 -> 63
A12: Rejected reference runs | B12: ='Source actuals'!B22 -> 6
A13: Recorded reference runs | B13: =SUM(B11:B12) -> 69
A14: Reference acceptance fraction | B14: =B11/B13 -> 0.91304348
A16: Run-count difference | B16: =B13-B11-B12 -> 0 | C16: =IF(B16=0,"RECONCILED","REVIEW") -> RECONCILED
A26: Completed work packages and reference acceptance are separate operating measures. Rejected trials remain in the denominator, and workforce ratios do not claim unused capacity.
A30: Control: formulas link to source actuals; reconciliation checks must read RECONCILED. Ratios describe the reported period and do not constitute forecast or mission readiness.

Sheet Quarter bridge
A1: Quarter-to-quarter operating bridge
A3: Published 2019-10-15 | USD unless stated | Internal
A5: Which recognized revenue and cost movements explain the change from Q2 to Q3?
A7: Measure | B7: Value | C7: Check / share
A8: Q3 recognized revenue | B8: ='Source actuals'!G8 -> 2990000
A9: Q2 recognized revenue | B9: ='Source actuals'!F8 -> 2645000
A10: Revenue movement | B10: =B8-B9 -> 345000
A11: Revenue growth | B11: =B10/B9 -> 0.13043478
A12: Q3 operating expenses | B12: ='Source actuals'!G10 -> 3430700
A13: Q2 operating expenses | B13: ='Source actuals'!F10 -> 3034850
A14: Derived operating-result movement | B14: =B10-('Source actuals'!G9-'Source actuals'!F9)-(B12-B13) -> -181950
A15: Reported operating-result movement | B15: ='Source actuals'!G11-'Source actuals'!F11 -> -181950
A17: Operating bridge difference | B17: =B14-B15 -> 0 | C17: =IF(B17=0,"RECONCILED","REVIEW") -> RECONCILED
A26: The bridge reconciles revenue change, delivery-cost change and operating-expense change to the reported operating-result movement. It is an actual-period bridge, not a forecast or a causal attribution.
A30: Control: formulas link to source actuals; reconciliation checks must read RECONCILED. Ratios describe the reported period and do not constitute forecast or mission readiness.

Sheet Backlog commitments
A1: Backlog commitment scale
A3: Published 2019-10-15 | USD unless stated | Internal
A5: How large is remaining contracted work relative to current-quarter revenue and period-end headcount?
A7: Measure | B7: Value | C7: Check / share
A8: Contracted backlog | B8: ='Source actuals'!B19 -> 23920000
A9: Current-quarter revenue | B9: ='Source actuals'!B8 -> 2990000
A10: Backlog / quarter revenue | B10: =B8/B9 -> 8
A11: Period-end headcount | B11: ='Source actuals'!B12 -> 73
A12: Backlog / period-end employee | B12: =B8/B11 -> 327671.23
A14: Backlog source difference | B14: =B8-'Source actuals'!B19 -> 0 | C14: =IF(B14=0,"RECONCILED","REVIEW") -> RECONCILED
A26: Backlog coverage and backlog per employee describe commitment scale at a point in time. They are not collection forecasts, cash balances, resource reserves or proof of available delivery capacity.
A30: Control: formulas link to source actuals; reconciliation checks must read RECONCILED. Ratios describe the reported period and do not constitute forecast or mission readiness.

Sheet Methodology
A1: Methodology and evidence boundaries
A3: Published 2019-10-15 | USD unless stated | Internal
A5: Period and recognized source actuals: USD; Q3 2019; period ended 2019-09-30. Revenue $2,990,000; COGS $1,136,200; opex $3,430,700; operating result $-1,576,900. Recognize engineering and development revenue against accepted contracted work; do not recognize projected asteroid sales.
A8: Income reconciliation: Does recognized revenue cover delivery and operating costs? Operating result remains negative after both delivery costs and development spending; the reconciliation isolates the reported loss rather than presenting revenue as profit.
A11: Contracted service economics: How do the three service categories reconcile, and what share comes from engineering? Recognized service categories reconcile to revenue. Engineering share describes the revenue base; no category-level profit is inferred because delivery costs are not allocated by service category.
A14: Development spending intensity: How does research spending relate to revenue, workforce and total operating expense? Research spending per period-end employee and relative to revenue exposes the development load. These ratios are descriptive; no capitalization, cash burn or return on investment is inferred.
A17: Delivery capacity and evidence quality: How do delivered work and accepted or rejected trials relate to the workforce snapshot? Completed work packages and reference acceptance are separate operating measures. Rejected trials remain in the denominator, and workforce ratios do not claim unused capacity.
A20: Quarter-to-quarter operating bridge: Which recognized revenue and cost movements explain the change from Q2 to Q3? The bridge reconciles revenue change, delivery-cost change and operating-expense change to the reported operating-result movement. It is an actual-period bridge, not a forecast or a causal attribution.
A23: Backlog commitment scale: How large is remaining contracted work relative to current-quarter revenue and period-end headcount? Backlog coverage and backlog per employee describe commitment scale at a point in time. They are not collection forecasts, cash balances, resource reserves or proof of available delivery capacity.
A26: Methodology and limitations: Control interface revisions before combining independently tested subsystems. Principal risk: mass and power growth. Integrated ground prototypes remain development hardware. Continue the approved ground-development scope; no asteroid commodity revenue is included in the operating outlook. No forecast, balance sheet, liquidity estimate, resource valuation, or cash-flow conclusion is supplied. Formula-linked analyses use recognized USD amounts and period-end operating snapshots; changing source inputs updates the calculations without changing the stated business scope.
